mkterm/info.py
mkterm/app.py
mkterm/__init__.py
mkterm-1.0.4.dist-info/top_level.txt
mkterm-1.0.4.dist-info/entry_points.txt
mkterm-1.0.4.dist-info/METADATA
mkterm-1.0.4.dist-info/metadata.json
mkterm-1.0.4.dist-info/RECORD
mkterm-1.0.4.dist-info/DESCRIPTION.rst
mkterm-1.0.4.dist-info/WHEEL
