Metadata-Version: 2.0
Name: mkterm
Version: 1.0.4
Summary: Make multiple terminals
Home-page: http://github.com/leibrockoli/mkterm
Author: Steven Leibrock
Author-email: leibrockoli@gmail.com
License: MIT
Keywords: terminal emulator mkterm desktop
Platform: UNKNOWN
Classifier: Development Status :: 5 - Production/Stable
Classifier: Intended Audience :: Developers
Classifier: Programming Language :: Python :: 2
Classifier: Programming Language :: Python :: 2.6
Classifier: Programming Language :: Python :: 2.7
Classifier: Programming Language :: Python :: 3
Classifier: Programming Language :: Python :: 3.2
Classifier: Programming Language :: Python :: 3.3
Classifier: Programming Language :: Python :: 3.4
